__init__.py
deployr_connection.py
real_data_test.py
tests.py
deployrclient-0.0.1.dist-info/DESCRIPTION.rst
deployrclient-0.0.1.dist-info/METADATA
deployrclient-0.0.1.dist-info/RECORD
deployrclient-0.0.1.dist-info/WHEEL
deployrclient-0.0.1.dist-info/metadata.json
deployrclient-0.0.1.dist-info/top_level.txt
