Metadata-Version: 2.0
Name: deployrclient
Version: 0.0.1
Summary: Python client for deployr
Home-page: https://github.com/aras7/deployr-python-client
Author: Andres Arrieche
Author-email: andres.arrieche@telefonica.com
License: Apache
Platform: UNKNOWN
Classifier: Programming Language :: Python
Classifier: License :: OSI Approved :: Apache Software License
Requires-Dist: requests
